MANIFEST.in
README.rst
setup.py
J_Box/Audio.py
J_Box/ML.py
J_Box/__init__.py
J_Box/plots.py
J_box.egg-info/SOURCES.txt