Metadata-Version: 1.1
Name: J_box
Version: 0.1.3.2
Summary: This is a compilation of the tools that I use from day-to-day
Home-page: http://github.com/Djuboor/J_Box
Author: David N Juboor
Author-email: dnjuboor@gmail.com
License: MIT
Keywords: DavidJuboor DavidNJuboor Statistics ML MachineLearning
Platform: UNKNOWN
Classifier: Development Status :: 3 - Alpha
Classifier: License :: OSI Approved :: MIT License
Classifier: Programming Language :: Python :: 2.7
